setup.cfg
setup.py
evalexpr/__init__.py
evalexpr/evalexpr.py
evalexpr.egg-info/PKG-INFO
evalexpr.egg-info/SOURCES.txt
evalexpr.egg-info/dependency_links.txt
evalexpr.egg-info/entry_points.txt
evalexpr.egg-info/not-zip-safe
evalexpr.egg-info/top_level.txt