Metadata-Version: 1.0
Name: evalexpr
Version: 1.0dev
Summary: eval expression
Home-page: UNKNOWN
Author: remi robert
Author-email: UNKNOWN
License: UNKNOWN
Platform: UNKNOWN
